hito_mail/hito2lists.cfg.example
hito_mail/hito2lists.py
hito_mail/hito_export.cfg.example
hito_mail/hito_export.py
hito_mail/lists_tools/__init__.py
hito_mail/lists_tools/core.py
hito_mail/lists_tools/exceptions.py
hito_mail-22.11.2.dist-info/LICENSE
hito_mail-22.11.2.dist-info/METADATA
hito_mail-22.11.2.dist-info/WHEEL
hito_mail-22.11.2.dist-info/entry_points.txt
hito_mail-22.11.2.dist-info/top_level.txt
hito_mail-22.11.2.dist-info/RECORD
