Metadata-Version: 2.1
Name: hito-mail
Version: 22.11.2
Summary: Gestion de listes d'email Zimbra ou LISTSERV à partir de Hito
Author-email: Michel Jouvin <michel.jouvin@ijclab.in2p3.fr>
License: BSD 3-Clause License
Project-URL: Homepage, https://gitlab.in2p3.fr/hito/mail_tools
Project-URL: Bug Tracker, https://gitlab.in2p3.fr/hito/mail_tools/-/issues
Classifier: License :: OSI Approved :: MIT License
Classifier: Operating System :: OS Independent
Classifier: Programming Language :: Python :: 3
Requires-Python: >=3.8
License-File: LICENSE
Requires-Dist: hito-tools (>=22.11)
Requires-Dist: pexpect
Requires-Dist: pyyaml
Requires-Dist: unidecode
